ardour2fxp.py
fxp2ardour.py
ardour2fxp-0.2.0.dist-info/LICENSE.txt
ardour2fxp-0.2.0.dist-info/METADATA
ardour2fxp-0.2.0.dist-info/WHEEL
ardour2fxp-0.2.0.dist-info/entry_points.txt
ardour2fxp-0.2.0.dist-info/top_level.txt
ardour2fxp-0.2.0.dist-info/RECORD
